[
  { "id": "srv-1", "name": "Server-1", "machine_type": "n2-standard-4", "cpu_count": 4, "cpu_usage_percent": 0, "gpu_count": 0, "max_gpu_usage_percent": null, "network_traffic": 0, "monthly_cost": 50.0, "is_dev_environment": false, "open_ports": ["443"] },
  { "id": "srv-2", "name": "Server-2", "machine_type": "n2-standard-2", "cpu_count": 2, "cpu_usage_percent": 0, "gpu_count": 0, "max_gpu_usage_percent": null, "network_traffic": 0, "monthly_cost": 30.0, "is_dev_environment": true, "open_ports": ["80", "443"] },
  { "id": "srv-3", "name": "Server-3", "machine_type": "n2-highmem-4", "cpu_count": 4, "cpu_usage_percent": 0, "gpu_count": 0, "max_gpu_usage_percent": null, "network_traffic": 0, "monthly_cost": 80.0, "is_dev_environment": false, "open_ports": ["443", "3306"] },
  { "id": "srv-4", "name": "Server-4", "machine_type": "n1-standard-1", "cpu_count": 1, "cpu_usage_percent": 0, "gpu_count": 0, "max_gpu_usage_percent": null, "network_traffic": 0, "monthly_cost": 25.0, "is_dev_environment": true, "open_ports": ["8080"] },
  { "id": "srv-5", "name": "Server-5", "machine_type": "n2-standard-8", "cpu_count": 8, "cpu_usage_percent": 0, "gpu_count": 0, "max_gpu_usage_percent": null, "network_traffic": 0, "monthly_cost": 150.0, "is_dev_environment": false, "open_ports": ["443"] },
  { "id": "srv-6", "name": "Server-6", "machine_type": "g2-standard-4", "cpu_count": 4, "cpu_usage_percent": 30, "gpu_count": 1, "max_gpu_usage_percent": 5, "network_traffic": 150, "monthly_cost": 400.0, "is_dev_environment": false, "open_ports": ["443"] },
  { "id": "srv-7", "name": "Server-7", "machine_type": "a2-highgpu-1g", "cpu_count": 12, "cpu_usage_percent": 45, "gpu_count": 1, "max_gpu_usage_percent": 8, "network_traffic": 500, "monthly_cost": 900.0, "is_dev_environment": true, "open_ports": ["443", "22"] },
  { "id": "srv-8", "name": "Server-8", "machine_type": "g2-standard-8", "cpu_count": 8, "cpu_usage_percent": 60, "gpu_count": 1, "max_gpu_usage_percent": 2, "network_traffic": 250, "monthly_cost": 600.0, "is_dev_environment": false, "open_ports": ["443", "80"] },
  { "id": "srv-9", "name": "Server-9", "machine_type": "a2-highgpu-2g", "cpu_count": 24, "cpu_usage_percent": 25, "gpu_count": 2, "max_gpu_usage_percent": 9, "network_traffic": 800, "monthly_cost": 1800.0, "is_dev_environment": true, "open_ports": ["443"] },
  { "id": "srv-10", "name": "Server-10", "machine_type": "g2-standard-4", "cpu_count": 4, "cpu_usage_percent": 15, "gpu_count": 1, "max_gpu_usage_percent": 1, "network_traffic": 100, "monthly_cost": 400.0, "is_dev_environment": false, "open_ports": ["443"] },
  { "id": "srv-11", "name": "Server-11", "machine_type": "n2-standard-4", "cpu_count": 4, "cpu_usage_percent": 40, "gpu_count": 0, "max_gpu_usage_percent": null, "network_traffic": 600, "monthly_cost": 50.0, "is_dev_environment": false, "open_ports": ["443", "0.0.0.0/0"] },
  { "id": "srv-12", "name": "Server-12", "machine_type": "n2-highcpu-8", "cpu_count": 8, "cpu_usage_percent": 65, "gpu_count": 0, "max_gpu_usage_percent": null, "network_traffic": 1200, "monthly_cost": 100.0, "is_dev_environment": true, "open_ports": ["80", "0.0.0.0/0"] },
  { "id": "srv-13", "name": "Server-13", "machine_type": "n2-standard-2", "cpu_count": 2, "cpu_usage_percent": 20, "gpu_count": 0, "max_gpu_usage_percent": null, "network_traffic": 300, "monthly_cost": 30.0, "is_dev_environment": false, "open_ports": ["443", "22", "0.0.0.0/0"] },
  { "id": "srv-14", "name": "Server-14", "machine_type": "e2-micro", "cpu_count": 2, "cpu_usage_percent": 85, "gpu_count": 0, "max_gpu_usage_percent": null, "network_traffic": 50, "monthly_cost": 10.0, "is_dev_environment": true, "open_ports": ["8080", "0.0.0.0/0"] },
  { "id": "srv-15", "name": "Server-15", "machine_type": "n2-standard-8", "cpu_count": 8, "cpu_usage_percent": 95, "gpu_count": 0, "max_gpu_usage_percent": null, "network_traffic": 450, "monthly_cost": 160.0, "is_dev_environment": false, "open_ports": ["443", "6379"] },
  { "id": "srv-16", "name": "Server-16", "machine_type": "n2-highmem-16", "cpu_count": 16, "cpu_usage_percent": 40, "gpu_count": 0, "max_gpu_usage_percent": null, "network_traffic": 2500, "monthly_cost": 350.0, "is_dev_environment": false, "open_ports": ["443", "5432"] },
  { "id": "srv-17", "name": "Server-17", "machine_type": "g2-standard-8", "cpu_count": 8, "cpu_usage_percent": 80, "gpu_count": 1, "max_gpu_usage_percent": 85, "network_traffic": 900, "monthly_cost": 650.0, "is_dev_environment": false, "open_ports": ["443"] },
  { "id": "srv-18", "name": "Server-18", "machine_type": "n1-standard-2", "cpu_count": 2, "cpu_usage_percent": 35, "gpu_count": 0, "max_gpu_usage_percent": null, "network_traffic": 120, "monthly_cost": 45.0, "is_dev_environment": true, "open_ports": ["443"] },
  { "id": "srv-19", "name": "Server-19", "machine_type": "e2-medium", "cpu_count": 2, "cpu_usage_percent": 55, "gpu_count": 0, "max_gpu_usage_percent": null, "network_traffic": 80, "monthly_cost": 25.0, "is_dev_environment": true, "open_ports": ["443", "3000"] },
  { "id": "srv-20", "name": "Server-20", "machine_type": "n2-standard-4", "cpu_count": 4, "cpu_usage_percent": 75, "gpu_count": 0, "max_gpu_usage_percent": null, "network_traffic": 700, "monthly_cost": 85.0, "is_dev_environment": false, "open_ports": ["443", "80"] },
  { "id": "srv-21", "name": "Server-21", "machine_type": "c2-standard-4", "cpu_count": 4, "cpu_usage_percent": 90, "gpu_count": 0, "max_gpu_usage_percent": null, "network_traffic": 1500, "monthly_cost": 120.0, "is_dev_environment": false, "open_ports": ["443"] },
  { "id": "srv-22", "name": "Server-22", "machine_type": "n2-highcpu-16", "cpu_count": 16, "cpu_usage_percent": 25, "gpu_count": 0, "max_gpu_usage_percent": null, "network_traffic": 3000, "monthly_cost": 200.0, "is_dev_environment": false, "open_ports": ["443"] },
  { "id": "srv-23", "name": "Server-23", "machine_type": "a2-highgpu-1g", "cpu_count": 12, "cpu_usage_percent": 98, "gpu_count": 1, "max_gpu_usage_percent": 95, "network_traffic": 4000, "monthly_cost": 900.0, "is_dev_environment": false, "open_ports": ["443"] },
  { "id": "srv-24", "name": "Server-24", "machine_type": "e2-small", "cpu_count": 2, "cpu_usage_percent": 45, "gpu_count": 0, "max_gpu_usage_percent": null, "network_traffic": 30, "monthly_cost": 15.0, "is_dev_environment": true, "open_ports": ["80", "443"] }
]
